odoo/addons/maintenance_project/README.rst
odoo/addons/maintenance_project/__init__.py
odoo/addons/maintenance_project/__manifest__.py
odoo/addons/maintenance_project/demo/demo_maintenance_project.xml
odoo/addons/maintenance_project/i18n/es.po
odoo/addons/maintenance_project/i18n/it.po
odoo/addons/maintenance_project/i18n/maintenance_project.pot
odoo/addons/maintenance_project/i18n/pt_BR.po
odoo/addons/maintenance_project/migrations/18.0.1.1.0/pre-migration.py
odoo/addons/maintenance_project/models/__init__.py
odoo/addons/maintenance_project/models/maintenance_equipment.py
odoo/addons/maintenance_project/models/maintenance_request.py
odoo/addons/maintenance_project/models/project_milestone.py
odoo/addons/maintenance_project/models/project_project.py
odoo/addons/maintenance_project/readme/CONTRIBUTORS.md
odoo/addons/maintenance_project/readme/DESCRIPTION.md
odoo/addons/maintenance_project/report/maintenance_request_report.xml
odoo/addons/maintenance_project/static/description/icon.png
odoo/addons/maintenance_project/static/description/index.html
odoo/addons/maintenance_project/tests/__init__.py
odoo/addons/maintenance_project/tests/test_maintenance_project.py
odoo/addons/maintenance_project/views/maintenance_equipment_views.xml
odoo/addons/maintenance_project/views/maintenance_request_views.xml
odoo/addons/maintenance_project/views/project_milestone.xml
odoo/addons/maintenance_project/views/project_project_views.xml
odoo_addon_maintenance_project-18.0.1.2.0.2.dist-info/METADATA
odoo_addon_maintenance_project-18.0.1.2.0.2.dist-info/WHEEL
odoo_addon_maintenance_project-18.0.1.2.0.2.dist-info/top_level.txt
odoo_addon_maintenance_project-18.0.1.2.0.2.dist-info/RECORD
